.DS_Store
sta663yw261.py
pkg/__init__.py
pkg/dist.py
pkg/k_means.py
pkg/k_means_int.py
pkg/k_means_pp.py
pkg/scalable_k_means_pp.py
sta663yw261-2.0.0.data/scripts/run_sta663.py
sta663yw261-2.0.0.dist-info/DESCRIPTION.rst
sta663yw261-2.0.0.dist-info/METADATA
sta663yw261-2.0.0.dist-info/RECORD
sta663yw261-2.0.0.dist-info/WHEEL
sta663yw261-2.0.0.dist-info/metadata.json
sta663yw261-2.0.0.dist-info/top_level.txt
