Metadata-Version: 2.0
Name: sta663yw261
Version: 2.0.0
Summary: Sta663 Final Project
Home-page: https://github.com/wyx951029
Author: Yixuan Wang
Author-email: yixuan.wang@duke.edu
License: MIT
Platform: UNKNOWN
Requires-Python: >=3
